wilight/__init__.py
wilight/const.py
wilight/discovery.py
wilight/protocol.py
wilight/ssdp.py
wilight/subscribe.py
wilight/support.py
wilight/util.py
wilight/wilight_device/__init__.py
wilight/wilight_device/api/__init__.py
wilight/wilight_device/api/xsd/__init__.py
wilight/wilight_device/api/xsd/device.py
wilight-0.0.79.dist-info/LICENSE
wilight-0.0.79.dist-info/METADATA
wilight-0.0.79.dist-info/WHEEL
wilight-0.0.79.dist-info/top_level.txt
wilight-0.0.79.dist-info/RECORD
