Metadata-Version: 2.1
Name: wilight
Version: 0.0.79
Summary: Python client for WiLight
Home-page: https://github.com/leofig-rj/python-wilight
Author: Leonardo Figueiro
Author-email: leoagfig@gmail.com
License: UNKNOWN
Platform: UNKNOWN
Classifier: Programming Language :: Python :: 3
Classifier: License :: OSI Approved :: MIT License
Classifier: Operating System :: OS Independent
Requires-Python: >=3.6
